odoo8_addon_account_journal_report_xls-8.0.0.2.0.99.dev22-py2.7-nspkg.pth
odoo8_addon_account_journal_report_xls-8.0.0.2.0.99.dev22.dist-info/DESCRIPTION.rst
odoo8_addon_account_journal_report_xls-8.0.0.2.0.99.dev22.dist-info/METADATA
odoo8_addon_account_journal_report_xls-8.0.0.2.0.99.dev22.dist-info/RECORD
odoo8_addon_account_journal_report_xls-8.0.0.2.0.99.dev22.dist-info/WHEEL
odoo8_addon_account_journal_report_xls-8.0.0.2.0.99.dev22.dist-info/metadata.json
odoo8_addon_account_journal_report_xls-8.0.0.2.0.99.dev22.dist-info/namespace_packages.txt
odoo8_addon_account_journal_report_xls-8.0.0.2.0.99.dev22.dist-info/top_level.txt
odoo_addons/account_journal_report_xls/README.rst
odoo_addons/account_journal_report_xls/__init__.py
odoo_addons/account_journal_report_xls/__openerp__.py
odoo_addons/account_journal_report_xls/account_journal.py
odoo_addons/account_journal_report_xls/i18n/de.po
odoo_addons/account_journal_report_xls/i18n/es_ES.po
odoo_addons/account_journal_report_xls/i18n/fr.po
odoo_addons/account_journal_report_xls/i18n/it.po
odoo_addons/account_journal_report_xls/i18n/lt.po
odoo_addons/account_journal_report_xls/i18n/nl.po
odoo_addons/account_journal_report_xls/i18n/sl.po
odoo_addons/account_journal_report_xls/report/__init__.py
odoo_addons/account_journal_report_xls/report/nov_account_journal.py
odoo_addons/account_journal_report_xls/report/nov_account_journal.rml
odoo_addons/account_journal_report_xls/report/nov_account_journal_xls.py
odoo_addons/account_journal_report_xls/static/description/icon.png
odoo_addons/account_journal_report_xls/static/description/icon.svg
odoo_addons/account_journal_report_xls/tests/export_csv_journal_by_fiscal_year.yml
odoo_addons/account_journal_report_xls/tests/export_csv_journal_by_period.yml
odoo_addons/account_journal_report_xls/tests/print_journal_by_fiscal_year.yml
odoo_addons/account_journal_report_xls/tests/print_journal_by_period.yml
odoo_addons/account_journal_report_xls/wizard/__init__.py
odoo_addons/account_journal_report_xls/wizard/print_journal_wizard.py
odoo_addons/account_journal_report_xls/wizard/print_journal_wizard.xml
